{"trial_id": "040", "hyperparameters": {"space": [{"class_name": "Int", "config": {"name": "n_layers", "default": null, "conditions": [], "min_value": 1, "max_value": 2, "step": 1, "sampling": "linear"}}, {"class_name": "Choice", "config": {"name": "filters_0", "default": 8, "conditions": [], "values": [8, 16, 32, 64, 96, 128], "ordered": true}}, {"class_name": "Int", "config": {"name": "kernel_size_0", "default": null, "conditions": [], "min_value": 2, "max_value": 8, "step": 1, "sampling": "linear"}}, {"class_name": "Choice", "config": {"name": "0_l2Reg", "default": 0.01, "conditions": [], "values": [0.01, 0.001, 0.0001], "ordered": true}}, {"class_name": "Choice", "config": {"name": "dropout_rate0", "default": 0.2, "conditions": [], "values": [0.2, 0.3, 0.4], "ordered": true}}, {"class_name": "Int", "config": {"name": "dense_units", "default": null, "conditions": [], "min_value": 32, "max_value": 256, "step": 32, "sampling": "linear"}}, {"class_name": "Float", "config": {"name": "dense_dropout", "default": 0.2, "conditions": [], "min_value": 0.2, "max_value": 0.5, "step": 0.1, "sampling": "linear"}}, {"class_name": "Choice", "config": {"name": "optimizer", "default": "adam", "conditions": [], "values": ["adam", "rmsprop", "sgd"], "ordered": false}}, {"class_name": "Choice", "config": {"name": "learning_rate", "default": 0.01, "conditions": [], "values": [0.01, 0.001, 0.0001], "ordered": true}}, {"class_name": "Choice", "config": {"name": "loss", "default": "binary_crossentropy", "conditions": [], "values": ["binary_crossentropy"], "ordered": false}}, {"class_name": "Choice", "config": {"name": "filters_1", "default": 8, "conditions": [], "values": [8, 16, 32, 64, 96, 128], "ordered": true}}, {"class_name": "Int", "config": {"name": "kernel_size_1", "default": null, "conditions": [], "min_value": 2, "max_value": 8, "step": 1, "sampling": "linear"}}, {"class_name": "Choice", "config": {"name": "1_l2Reg", "default": 0.01, "conditions": [], "values": [0.01, 0.001, 0.0001], "ordered": true}}, {"class_name": "Choice", "config": {"name": "dropout_rate1", "default": 0.2, "conditions": [], "values": [0.2, 0.3, 0.4], "ordered": true}}], "values": {"n_layers": 1, "filters_0": 128, "kernel_size_0": 8, "0_l2Reg": 0.001, "dropout_rate0": 0.4, "dense_units": 96, "dense_dropout": 0.2, "optimizer": "adam", "learning_rate": 0.01, "loss": "binary_crossentropy", "filters_1": 64, "kernel_size_1": 6, "1_l2Reg": 0.0001, "dropout_rate1": 0.4}}, "metrics": {"metrics": {"AUC": {"direction": "max", "observations": [{"value": [0.9870651364326477], "step": 112}]}, "accuracy": {"direction": "max", "observations": [{"value": [0.9351385235786438], "step": 112}]}, "loss": {"direction": "min", "observations": [{"value": [0.1768459528684616], "step": 112}]}, "mae": {"direction": "min", "observations": [{"value": [0.09043415635824203], "step": 112}]}, "val_AUC": {"direction": "max", "observations": [{"value": [0.9911158084869385], "step": 112}]}, "val_accuracy": {"direction": "max", "observations": [{"value": [0.9501259326934814], "step": 112}]}, "val_loss": {"direction": "min", "observations": [{"value": [0.1520405411720276], "step": 112}]}, "val_mae": {"direction": "min", "observations": [{"value": [0.07571916282176971], "step": 112}]}, "learning_rate": {"direction": "min", "observations": [{"value": [0.0024999999441206455], "step": 112}]}}}, "score": 0.9501259326934814, "best_step": 112, "status": "COMPLETED", "message": null}